magic_marker/__init__.py
magic_marker/cli.py
magic_marker/fixable.py
magic_marker/fixes.py
magic_marker/magic_marker.py
magic_marker-1.0.0.dist-info/LICENSE
magic_marker-1.0.0.dist-info/METADATA
magic_marker-1.0.0.dist-info/WHEEL
magic_marker-1.0.0.dist-info/entry_points.txt
magic_marker-1.0.0.dist-info/top_level.txt
magic_marker-1.0.0.dist-info/RECORD
