Metadata-Version: 2.1
Name: magic-marker
Version: 1.0.0
Summary: Automatically mark pytest tests with a UUID
Home-page: https://github.com/rcbops/magic-marker
Author: rcbops
Author-email: rpc-automation@rackspace.com
Maintainer: rcbops
Maintainer-email: rpc-automation@rackspace.com
License: Apache Software License 2.0
Keywords: magic_marker
Platform: UNKNOWN
Classifier: Development Status :: 4 - Beta
Classifier: Intended Audience :: Developers
Classifier: License :: OSI Approved :: Apache Software License
Classifier: Natural Language :: English
Classifier: Programming Language :: Python :: 2
Classifier: Programming Language :: Python :: 2.7
Classifier: Programming Language :: Python :: 3
Classifier: Programming Language :: Python :: 3.4
Classifier: Programming Language :: Python :: 3.5
Classifier: Programming Language :: Python :: 3.6
Classifier: Operating System :: OS Independent
Requires-Dist: Click (>=6.0)
Requires-Dist: flake8-pytest-mark (<2.0.0,>=1.0.0)
Requires-Dist: flake8
Requires-Dist: flake8-json
Requires-Dist: six
